[
  {
    "id": "act_0001",
    "title": "Theme Song Move",
    "description": "Pick a theme song and play it for 30 seconds. Bonus: do a dramatic entrance.",
    "is_civic": false,
    "time_bucket": "5",
    "time_min": 5,
    "effort": "light",
    "location": "either",
    "supports_solo": true,
    "lane": "Creative Spike",
    "vibe": "Playful",
    "category": "play"
  },
  {
    "id": "act_0002",
    "title": "Nature Color Hunt",
    "description": "Find 3 colors outside in 5 minutes. Bonus: make one surprising.",
    "is_civic": false,
    "time_bucket": "5",
    "time_min": 5,
    "effort": "light",
    "location": "outdoor",
    "supports_solo": true,
    "lane": "Energy Reset",
    "vibe": "Light",
    "category": "outdoor"
  },
  {
    "id": "act_0003",
    "title": "Two‑Minute Story",
    "description": "Tell a 2‑minute story where every sentence starts with “Suddenly…”.",
    "is_civic": false,
    "time_bucket": "10",
    "time_min": 10,
    "effort": "med",
    "location": "indoor",
    "supports_solo": true,
    "lane": "Meaning‑Light",
    "vibe": "Warm",
    "category": "conversation"
  },
  {
    "id": "act_0004",
    "title": "Desk Reset",
    "description": "Clear one tiny surface for 3 minutes. Stop when it looks calmer.",
    "is_civic": false,
    "time_bucket": "5",
    "time_min": 5,
    "effort": "light",
    "location": "indoor",
    "supports_solo": true,
    "lane": "Energy Reset",
    "vibe": "Calm",
    "category": "reset"
  },
  {
    "id": "act_0005",
    "title": "Dance Break",
    "description": "Do a 45‑second dance. Any style. Yes, it counts.",
    "is_civic": false,
    "time_bucket": "5",
    "time_min": 5,
    "effort": "med",
    "location": "either",
    "supports_solo": true,
    "lane": "Creative Spike",
    "vibe": "Playful",
    "category": "movement"
  },
  {
    "id": "act_0006",
    "title": "Micro Stretch",
    "description": "Stretch your tightest spot for 90 seconds. Then stop.",
    "is_civic": false,
    "time_bucket": "5",
    "time_min": 5,
    "effort": "light",
    "location": "either",
    "supports_solo": true,
    "lane": "Energy Reset",
    "vibe": "Calm",
    "category": "movement"
  },
  {
    "id": "act_0007",
    "title": "Kitchen Remix",
    "description": "Invent a new snack combo using whatever’s nearby. Rate it 1–10.",
    "is_civic": false,
    "time_bucket": "10",
    "time_min": 10,
    "effort": "med",
    "location": "indoor",
    "supports_solo": false,
    "lane": "Creative Spike",
    "vibe": "Playful",
    "category": "food"
  },
  {
    "id": "act_0008",
    "title": "Future‑You Gift",
    "description": "Do one 3‑minute thing your future self will thank you for.",
    "is_civic": false,
    "time_bucket": "10",
    "time_min": 10,
    "effort": "med",
    "location": "indoor",
    "supports_solo": true,
    "lane": "Meaning‑Light",
    "vibe": "Steady",
    "category": "life"
  },
  {
    "id": "act_0009",
    "title": "Gratitude Text",
    "description": "Send one short, specific thank‑you text. No overthinking.",
    "is_civic": true,
    "time_bucket": "5",
    "time_min": 5,
    "effort": "light",
    "location": "either",
    "supports_solo": true,
    "lane": "Kindness",
    "vibe": "Warm",
    "category": "community"
  },
  {
    "id": "act_0010",
    "title": "Compliment Drop",
    "description": "Give one specific compliment to someone. One sentence.",
    "is_civic": true,
    "time_bucket": "5",
    "time_min": 5,
    "effort": "light",
    "location": "either",
    "supports_solo": true,
    "lane": "Kindness",
    "vibe": "Warm",
    "category": "community"
  },
  {
    "id": "act_0011",
    "title": "Donation Door Pile",
    "description": "Pick one item to donate and put it by the door.",
    "is_civic": true,
    "time_bucket": "10",
    "time_min": 10,
    "effort": "light",
    "location": "indoor",
    "supports_solo": true,
    "lane": "Community",
    "vibe": "Steady",
    "category": "community"
  },
  {
    "id": "act_0012",
    "title": "Trash Grab 5",
    "description": "Safely pick up 5 pieces of litter. Quick and done.",
    "is_civic": true,
    "time_bucket": "10",
    "time_min": 10,
    "effort": "med",
    "location": "outdoor",
    "supports_solo": true,
    "lane": "Community",
    "vibe": "Steady",
    "category": "community"
  },
  {
    "id": "act_0013",
    "title": "Helpful Comment",
    "description": "Leave one kind + useful comment in a local group online.",
    "is_civic": true,
    "time_bucket": "+10",
    "time_min": 15,
    "effort": "med",
    "location": "indoor",
    "supports_solo": true,
    "lane": "Community",
    "vibe": "Steady",
    "category": "community"
  },
  {
    "id": "act_0014",
    "title": "Neighbor Note",
    "description": "Write one thing you love about where you live. Save it.",
    "is_civic": true,
    "time_bucket": "5",
    "time_min": 5,
    "effort": "light",
    "location": "either",
    "supports_solo": true,
    "lane": "Meaning‑Light",
    "vibe": "Warm",
    "category": "community"
  },
  {
    "id": "act_0015",
    "title": "Tiny Favor Offer",
    "description": "Offer a small favor (ride, pickup, watch a pet). If no one needs it, you tried.",
    "is_civic": true,
    "time_bucket": "+10",
    "time_min": 15,
    "effort": "high",
    "location": "either",
    "supports_solo": true,
    "lane": "Kindness",
    "vibe": "Warm",
    "category": "community"
  },
  {
    "id": "act_0016",
    "title": "Library Hold",
    "description": "Place one library hold (book/audiobook). Tiny future joy.",
    "is_civic": true,
    "time_bucket": "10",
    "time_min": 10,
    "effort": "light",
    "location": "indoor",
    "supports_solo": true,
    "lane": "Community",
    "vibe": "Playful",
    "category": "community"
  },
  {
    "id": "act_0017",
    "title": "Local Link Save",
    "description": "Look up one local issue and save one link. That’s it.",
    "is_civic": true,
    "time_bucket": "+10",
    "time_min": 15,
    "effort": "med",
    "location": "indoor",
    "supports_solo": true,
    "lane": "Civic",
    "vibe": "Steady",
    "category": "civic"
  },
  {
    "id": "act_0018",
    "title": "Sign One Petition",
    "description": "Find a credible petition and sign once. Stop there.",
    "is_civic": true,
    "time_bucket": "10",
    "time_min": 10,
    "effort": "med",
    "location": "indoor",
    "supports_solo": true,
    "lane": "Civic",
    "vibe": "Steady",
    "category": "civic"
  },
  {
    "id": "act_0019",
    "title": "Call a Rep (2 min)",
    "description": "Find the right office and save the number. Calling is optional today.",
    "is_civic": true,
    "time_bucket": "+10",
    "time_min": 15,
    "effort": "high",
    "location": "indoor",
    "supports_solo": true,
    "lane": "Civic",
    "vibe": "Steady",
    "category": "civic"
  },
  {
    "id": "act_0020",
    "title": "Community Event Peek",
    "description": "Find one local event and add it to your calendar as ‘maybe’.",
    "is_civic": true,
    "time_bucket": "10",
    "time_min": 10,
    "effort": "light",
    "location": "indoor",
    "supports_solo": true,
    "lane": "Community",
    "vibe": "Warm",
    "category": "community"
  }
]